<?xml version="1.0" encoding="UTF-8" ?>
<products>
    <product>
        <id>1</id>
        <serialNumber>1316546541</serialNumber>
        <employeeId>1</employeeId>
        <typeId>1</typeId>
    </product>
    <product>
        <id>2</id>
        <serialNumber>65413213</serialNumber>
        <employeeId>1</employeeId>
        <typeId>2</typeId>
    </product>
    <product>
        <id>3</id>
        <serialNumber>6456546541</serialNumber>
        <employeeId>1</employeeId>
        <typeId>3</typeId>
    </product>
    <product>
        <id>4</id>
        <serialNumber>684541654</serialNumber>
        <employeeId>2</employeeId>
        <typeId>1</typeId>
    </product>
    <product>
        <id>5</id>
        <serialNumber>16545123146</serialNumber>
        <employeeId>3</employeeId>
        <typeId>4</typeId>
    </product>
    <product>
        <id>6</id>
        <serialNumber>64123479108</serialNumber>
        <employeeId>4</employeeId>
        <typeId>4</typeId>
    </product>
    <product>
        <id>8</id>
        <serialNumber>123456</serialNumber>
        <employeeId>4</employeeId>
        <typeId>2</typeId>
    </product>
    <product>
        <id>9</id>
        <serialNumber>666</serialNumber>
        <employeeId>4</employeeId>
        <typeId>2</typeId>
    </product>
</products>
